nmfishingreport/__init__.py
nmfishingreport/__main__.py
nmfishingreport/internet_on.py
nmfishingreport/nmfishingreport.py
nmfishingreport-0.1.3.dist-info/LICENSE
nmfishingreport-0.1.3.dist-info/METADATA
nmfishingreport-0.1.3.dist-info/WHEEL
nmfishingreport-0.1.3.dist-info/top_level.txt
nmfishingreport-0.1.3.dist-info/RECORD
