Metadata-Version: 2.1
Name: nmfishingreport
Version: 0.1.3
Summary: Scrapes the NM Dept of Game and Fish fishing report
Home-page: https://github.com/n8henrie/nmfishingreport
Author: Nathan Henrie
Author-email: nate@n8henrie.com
License: MIT
Keywords: nmfishingreport
Platform: UNKNOWN
Classifier: Natural Language :: English
Classifier: Programming Language :: Python :: 3
Classifier: Programming Language :: Python :: 3.8
Classifier: Programming Language :: Python :: 3.9
License-File: LICENSE
Requires-Dist: beautifulsoup4 (==4.9.3)
Provides-Extra: dev
Requires-Dist: black (==21.5b1) ; extra == 'dev'
Requires-Dist: build (==0.6.0.post1) ; extra == 'dev'
Requires-Dist: flake8 (==3.9.2) ; extra == 'dev'
Requires-Dist: pytest (==6.2.4) ; extra == 'dev'
Requires-Dist: tox (==3.23.1) ; extra == 'dev'
Requires-Dist: twine (==3.4.1) ; extra == 'dev'
Requires-Dist: wheel (==0.36.2) ; extra == 'dev'
